nameforme/__init__.py
nameforme/nameforme.py
nameforme-1.1.0.dist-info/METADATA
nameforme-1.1.0.dist-info/WHEEL
nameforme-1.1.0.dist-info/LICENSE
nameforme-1.1.0.dist-info/RECORD
