Metadata-Version: 2.1
Name: nameforme
Version: 1.1.0
Summary: A package used to generate names.
License: MIT
Author: Daniel Cairns, Eyre Hong, Bruce Wu, Zilong Yi (UBC MDS)
Requires-Python: >=3.9,<4.0
Classifier: License :: OSI Approved :: MIT License
Classifier: Programming Language :: Python :: 3
Classifier: Programming Language :: Python :: 3.9
Classifier: Programming Language :: Python :: 3.10
Classifier: Programming Language :: Python :: 3.11
Requires-Dist: jellyfish (>=0.9.0,<0.10.0)
Requires-Dist: numpy (>=1.24.1,<2.0.0)
Requires-Dist: pandas (>=1.5.3,<2.0.0)
Requires-Dist: pytest (>=7.2.1,<8.0.0)
